nibbler/__init__.py
nibbler/__main__.py
nibbler/nibbler.py
nibbler/opml.py
nibbler/resources/GitHub-Mark-32px.png
nibbler/resources/GitHub-Mark-Light-32px.png
nibbler/resources/email.html
nibbler/resources/mailfeed.pdf
nibbler/resources/mailfeed.png
nibbler/resources/mailfeed.svg
nibbler/resources/system.png
nibbler/templates/base_email.html
nibbler/templates/nibble.html
nibbler_rss-0.3.0.dist-info/LICENSE.txt
nibbler_rss-0.3.0.dist-info/METADATA
nibbler_rss-0.3.0.dist-info/WHEEL
nibbler_rss-0.3.0.dist-info/entry_points.txt
nibbler_rss-0.3.0.dist-info/top_level.txt
nibbler_rss-0.3.0.dist-info/RECORD
