Metadata-Version: 2.2
Name: nibbler-rss
Version: 0.3.0
Summary: A simple RSS to email application. Nibbler aggregates your subscriptions and puts them in an email.
Home-page: https://github.com/rrodakowski/nibbler
Author: Randall Rodakowski
Author-email: randall.rodakowski@gmail.com
License: LICENSE.txt
License-File: LICENSE.txt
Requires-Dist: lxml==5.1.0
Requires-Dist: SQLAlchemy==2.0.39
Requires-Dist: feedparser==6.0.11
Requires-Dist: Jinja2==3.1.6
Dynamic: author
Dynamic: author-email
Dynamic: description
Dynamic: description-content-type
Dynamic: home-page
Dynamic: license
Dynamic: requires-dist
Dynamic: summary
